odoo/addons/ssi_transaction_tax_address_mixin/README.rst
odoo/addons/ssi_transaction_tax_address_mixin/__init__.py
odoo/addons/ssi_transaction_tax_address_mixin/__manifest__.py
odoo/addons/ssi_transaction_tax_address_mixin/models/__init__.py
odoo/addons/ssi_transaction_tax_address_mixin/models/mixin_transaction_tax_address.py
odoo/addons/ssi_transaction_tax_address_mixin/models/res_partner.py
odoo/addons/ssi_transaction_tax_address_mixin/static/description/icon.png
odoo14_addon_ssi_transaction_tax_address_mixin-14.0.1.0.0.dist-info/METADATA
odoo14_addon_ssi_transaction_tax_address_mixin-14.0.1.0.0.dist-info/WHEEL
odoo14_addon_ssi_transaction_tax_address_mixin-14.0.1.0.0.dist-info/top_level.txt
odoo14_addon_ssi_transaction_tax_address_mixin-14.0.1.0.0.dist-info/RECORD
